Metadata-Version: 2.1
Name: cdnget
Version: 1.2.0
Summary: Utility to download files from public CDN (CDNJS/jsDelivr/UNPKG/Google)
Home-page: https://github.com/kwatch/cdnget/tree/python
Author: kwatch
Author-email: kwatch@gmail.com
License: MIT
Download-URL: https://pypi.python.org/packages/source/c/cdnget/cdnget-1.2.0.tar.gz
Platform: any
Classifier: Development Status :: 5 - Production/Stable
Classifier: Environment :: Console
Classifier: Intended Audience :: Developers
Classifier: License :: OSI Approved :: MIT License
Classifier: Operating System :: OS Independent
Classifier: Programming Language :: Python
Classifier: Programming Language :: Python :: 2.6
Classifier: Programming Language :: Python :: 2.7
Classifier: Programming Language :: Python :: 3
Classifier: Programming Language :: Python :: 3.3
Classifier: Programming Language :: Python :: 3.4
Classifier: Programming Language :: Python :: 3.5
Classifier: Programming Language :: Python :: 3.6
Classifier: Programming Language :: Python :: 3.7
Classifier: Programming Language :: Python :: 3.8
Classifier: Programming Language :: Python :: 3.9
Classifier: Programming Language :: Python :: 3.10
Classifier: Topic :: Software Development :: Libraries :: Python Modules
Classifier: Topic :: Internet :: WWW/HTTP :: Dynamic Content :: CGI Tools/Libraries
Provides-Extra: dev
Provides-Extra: test
License-File: LICENSE
